gersyll/__init__.py
gersyll-1.3.dist-info/LICENSE.txt
gersyll-1.3.dist-info/METADATA
gersyll-1.3.dist-info/WHEEL
gersyll-1.3.dist-info/top_level.txt
gersyll-1.3.dist-info/RECORD
